<?xml version="1.0" encoding="UTF-8"?>
<objects serializationModel="Studio.02.03.00">
	<object class="AudioFile" id="{bb19ae9a-7749-4988-9a39-8b475f395644}">
		<property name="assetPath">
			<value>UI/MenuButtonStart.ogg</value>
		</property>
		<property name="frequencyInKHz">
			<value>48</value>
		</property>
		<property name="channelCount">
			<value>1</value>
		</property>
		<property name="length">
			<value>3.2998333333333334</value>
		</property>
		<relationship name="masterAssetFolder">
			<destination>{b7c981d0-b246-4d0a-b1c3-cec0e31aacf1}</destination>
		</relationship>
	</object>
</objects>
